LICENSE
MANIFEST.in
README.md
setup.cfg
setup.py
versioneer.py
rball/__init__.py
rball/_version.py
rball/rballlike.py
rball/response_database.py
rball.egg-info/PKG-INFO
rball.egg-info/SOURCES.txt
rball.egg-info/dependency_links.txt
rball.egg-info/requires.txt
rball.egg-info/top_level.txt
rball/io/__init__.py
rball/utils/__init__.py
rball/utils/grid_generator.py
rball/utils/logging.py
rball/utils/package_data.py